iparq/__init__.py
iparq/py.typed
iparq/source.py
iparq-0.4.1.dist-info/METADATA
iparq-0.4.1.dist-info/WHEEL
iparq-0.4.1.dist-info/entry_points.txt
iparq-0.4.1.dist-info/licenses/LICENSE
iparq-0.4.1.dist-info/RECORD
