Metadata-Version: 2.4
Name: iparq
Version: 0.4.1
Summary: Display version compression and bloom filter information about a parquet file
Author-email: MiguelElGallo <miguel.zurcher@gmail.com>
License-File: LICENSE
Requires-Python: >=3.9
Requires-Dist: pyarrow
Requires-Dist: pydantic
Requires-Dist: rich
Requires-Dist: typer
Provides-Extra: checks
Requires-Dist: mypy>=1.14.1; extra == 'checks'
Requires-Dist: ruff>=0.9.3; extra == 'checks'
Provides-Extra: test
Requires-Dist: pytest-cov>=4.0.0; extra == 'test'
Requires-Dist: pytest>=7.0; extra == 'test'
